{"sidebar_main-sidebar":{"combined_image_author_widget-2":{"title":"","name":"Harry May","text":"Strategy experience & analytical expertise combine to enable decision making  value.","image":"http:\/\/brainbizz.webgeniuslab.net\/wp-content\/uploads\/2018\/11\/author_widget1.jpg","signature":"http:\/\/brainbizz.webgeniuslab.net\/wp-content\/uploads\/2018\/11\/author_signature.png","facebook":"","twitter":"","linkedin":"","wpml_language":"all"},"search-2":{"title":""},"categories-2":{"title":"","count":1,"hierarchical":0,"dropdown":0},"wgl-posts-2":{"title":"Recent Posts","num_posts":"3","categories":"4","show_image":"on","show_related":"","show_content":"","show_date":"on"},"media_gallery-2":{"title":"Gallery","columns":3,"size":"thumbnail","link_type":"post","orderby_random":false,"ids":[84,76,75,74,77,78]},"tag_cloud-2":{"title":"","count":0,"taxonomy":"post_tag"},"combined_image_banner_widget-2":{"image":"http:\/\/brainbizz.webgeniuslab.net\/wp-content\/uploads\/2018\/11\/logo_banner.png","image_2":"http:\/\/brainbizz.webgeniuslab.net\/wp-content\/uploads\/2018\/11\/banner_bg.jpg","text_sub_title":"First-Class Finnance","text":"Experts","title":"get in touch","button_link":"http:\/\/brainbizz.webgeniuslab.net"}},"shop_products":{"woocommerce_product_search-2":{"title":""},"woocommerce_product_categories-2":{"title":"Product categories","orderby":"name","dropdown":0,"count":1,"hierarchical":1,"show_children_only":0,"hide_empty":1,"max_depth":"","wpml_language":"all"},"woocommerce_price_filter-2":{"title":"Filter by price"},"woocommerce_products-2":{"title":"Products","number":3,"show":"","orderby":"date","order":"desc","hide_free":0,"show_hidden":0},"woocommerce_product_tag_cloud-2":{"title":"Product tags"},"woocommerce_widget_cart-2":{"title":"Cart","hide_if_empty":0}}}